{
  "terminal": "Institutional Macro Terminal",
  "generated_at": "2026-05-23T04:33:02.941690Z",
  "market_regime": {
    "regime": "AI",
    "dominant_driver": "AI",
    "secondary_driver": "GENERAL",
    "signal_density": "LOW",
    "critical_alerts": 0,
    "high_alerts": 0,
    "last_updated": "2026-05-23T04:33:02.941701Z"
  },
  "top_signals": [
    {
      "id": "6d22c257a0c1c0cfffe23f6f198bdfb0",
      "title": "Ebola Outruns Containment in Eastern Congo as Contact Tracing Falters",
      "summary": "Ebola is spreading faster than responders can track it in eastern Congo, where health workers managed to follow up with barely one in five identified contacts in a single day.",
      "link": "https://www.bloomberg.com/news/articles/2026-05-23/ebola-outbreak-in-congo-outrunning-containment-as-contact-tracing-falters",
      "source": "Bloomberg",
      "score": 13,
      "severity": "MEDIUM",
      "regime": "AI",
      "tickers": [],
      "regions": [],
      "assets": [
        "AI"
      ],
      "market_impact": {
        "bullish": [
          "NVDA",
          "SEMIS",
          "QQQ"
        ],
        "bearish": []
      },
      "why_it_matters": "AI and semiconductor developments impacting technology leadership and capex cycles.",
      "published": "2026-05-23T04:32:20.423038Z"
    }
  ],
  "alerts": [
    {
      "id": "6d22c257a0c1c0cfffe23f6f198bdfb0",
      "title": "Ebola Outruns Containment in Eastern Congo as Contact Tracing Falters",
      "summary": "Ebola is spreading faster than responders can track it in eastern Congo, where health workers managed to follow up with barely one in five identified contacts in a single day.",
      "link": "https://www.bloomberg.com/news/articles/2026-05-23/ebola-outbreak-in-congo-outrunning-containment-as-contact-tracing-falters",
      "source": "Bloomberg",
      "score": 13,
      "severity": "MEDIUM",
      "regime": "AI",
      "tickers": [],
      "regions": [],
      "assets": [
        "AI"
      ],
      "market_impact": {
        "bullish": [
          "NVDA",
          "SEMIS",
          "QQQ"
        ],
        "bearish": []
      },
      "why_it_matters": "AI and semiconductor developments impacting technology leadership and capex cycles.",
      "published": "2026-05-23T04:32:20.423038Z"
    }
  ]
}