{
  "terminal": "Institutional Macro Terminal",
  "generated_at": "2026-06-08T06:41:34.554018Z",
  "market_regime": {
    "regime": "GEO-SHOCK",
    "dominant_driver": "GEO-SHOCK",
    "secondary_driver": "GENERAL",
    "signal_density": "LOW",
    "critical_alerts": 1,
    "high_alerts": 0,
    "last_updated": "2026-06-08T06:41:34.554028Z"
  },
  "top_signals": [
    {
      "id": "e4b249d9a5eb1eb0457d11679fdaf5bd",
      "title": "Oil Jumps as Iran and Israel Exchange Fire and Tensions Escalate",
      "summary": "Oil surged after Iran and Israel exchanged fire, threatening a fragile ceasefire in the Middle East as talks to end the war falter.",
      "link": "https://www.bloomberg.com/news/articles/2026-06-07/latest-oil-market-news-and-analysis-for-june-8",
      "source": "Bloomberg",
      "score": 51,
      "severity": "CRITICAL",
      "regime": "GEO-SHOCK",
      "tickers": [
        "WTI"
      ],
      "regions": [
        "MIDDLE_EAST"
      ],
      "assets": [
        "COMMODITIES"
      ],
      "market_impact": {
        "bullish": [
          "XAU",
          "WTI",
          "DXY",
          "DEFENSE"
        ],
        "bearish": [
          "SPY",
          "QQQ",
          "AIRLINES"
        ]
      },
      "why_it_matters": "Geopolitical escalation affecting commodities, shipping and cross-asset volatility.",
      "published": "2026-06-08T06:40:38.646752Z"
    },
    {
      "id": "8a368f95c612b09bdf38b4cc153636f2",
      "title": "Tate &amp; Lyle Latest Loss for London After Sale to US Rival",
      "summary": "Ingredion Inc. agreed to acquire UK-based rival Tate &amp; Lyle Plc for \u00a32.7 billion ($3.6 billion), marking another famous brand leaving the London stock market.",
      "link": "https://www.bloomberg.com/news/articles/2026-06-08/ingredion-agrees-to-buy-uk-rival-tate-lyle-for-2-7-billion",
      "source": "Bloomberg",
      "score": 9,
      "severity": "MEDIUM",
      "regime": "GENERAL",
      "tickers": [],
      "regions": [
        "UK"
      ],
      "assets": [],
      "market_impact": {},
      "why_it_matters": "Macro-sensitive market development.",
      "published": "2026-06-08T06:40:38.646809Z"
    }
  ],
  "alerts": [
    {
      "id": "e4b249d9a5eb1eb0457d11679fdaf5bd",
      "title": "Oil Jumps as Iran and Israel Exchange Fire and Tensions Escalate",
      "summary": "Oil surged after Iran and Israel exchanged fire, threatening a fragile ceasefire in the Middle East as talks to end the war falter.",
      "link": "https://www.bloomberg.com/news/articles/2026-06-07/latest-oil-market-news-and-analysis-for-june-8",
      "source": "Bloomberg",
      "score": 51,
      "severity": "CRITICAL",
      "regime": "GEO-SHOCK",
      "tickers": [
        "WTI"
      ],
      "regions": [
        "MIDDLE_EAST"
      ],
      "assets": [
        "COMMODITIES"
      ],
      "market_impact": {
        "bullish": [
          "XAU",
          "WTI",
          "DXY",
          "DEFENSE"
        ],
        "bearish": [
          "SPY",
          "QQQ",
          "AIRLINES"
        ]
      },
      "why_it_matters": "Geopolitical escalation affecting commodities, shipping and cross-asset volatility.",
      "published": "2026-06-08T06:40:38.646752Z"
    },
    {
      "id": "8a368f95c612b09bdf38b4cc153636f2",
      "title": "Tate &amp; Lyle Latest Loss for London After Sale to US Rival",
      "summary": "Ingredion Inc. agreed to acquire UK-based rival Tate &amp; Lyle Plc for \u00a32.7 billion ($3.6 billion), marking another famous brand leaving the London stock market.",
      "link": "https://www.bloomberg.com/news/articles/2026-06-08/ingredion-agrees-to-buy-uk-rival-tate-lyle-for-2-7-billion",
      "source": "Bloomberg",
      "score": 9,
      "severity": "MEDIUM",
      "regime": "GENERAL",
      "tickers": [],
      "regions": [
        "UK"
      ],
      "assets": [],
      "market_impact": {},
      "why_it_matters": "Macro-sensitive market development.",
      "published": "2026-06-08T06:40:38.646809Z"
    }
  ]
}