{
  "terminal": "Institutional Macro Terminal",
  "generated_at": "2026-06-29T10:06:23.068390Z",
  "market_regime": {
    "regime": "GEO-SHOCK",
    "dominant_driver": "GEO-SHOCK",
    "secondary_driver": "GENERAL",
    "signal_density": "LOW",
    "critical_alerts": 1,
    "high_alerts": 1,
    "last_updated": "2026-06-29T10:06:23.068402Z"
  },
  "top_signals": [
    {
      "id": "102bee1ec6a6816b4af992be4b2eb2c8",
      "title": "Dip Buyers Lift US Stocks Despite Rise in Oil: Markets Wrap",
      "summary": "Bargain hunters are pushing stocks higher at the start of a week in which leaders of the biggest central banks and a busy data calendar will set the tone. Oil rose after a weekend of tensions in the Middle East.",
      "link": "https://www.bloomberg.com/news/articles/2026-06-28/us-futures-climb-on-reports-peace-talks-to-resume-markets-wrap",
      "source": "Bloomberg",
      "score": 30,
      "severity": "CRITICAL",
      "regime": "GEO-SHOCK",
      "tickers": [
        "WTI"
      ],
      "regions": [],
      "assets": [
        "AI",
        "COMMODITIES",
        "EQUITIES"
      ],
      "market_impact": {
        "bullish": [
          "XAU",
          "WTI",
          "DXY",
          "DEFENSE"
        ],
        "bearish": [
          "SPY",
          "QQQ",
          "AIRLINES"
        ]
      },
      "why_it_matters": "Geopolitical escalation affecting commodities, shipping and cross-asset volatility.",
      "published": "2026-06-29T10:05:45.708993Z"
    },
    {
      "id": "39b329c8183c0fe4d5ecc0764a4204d7",
      "title": "UK Bond Yields Higher Ahead of Burnham Speech",
      "summary": "",
      "link": "https://www.bloomberg.com/news/live-blog/2026-06-29/ftse-100-live-pound-glits-us-iran-talks-hormuz-oil-prices-gold-what-s-moving-uk-markets-right-now-markets-today",
      "source": "Bloomberg",
      "score": 15,
      "severity": "HIGH",
      "regime": "RATES",
      "tickers": [],
      "regions": [
        "UK"
      ],
      "assets": [],
      "market_impact": {
        "bullish": [
          "DXY",
          "JPY"
        ],
        "bearish": [
          "TLT",
          "SPY",
          "QQQ"
        ]
      },
      "why_it_matters": "Central-bank repricing affecting yields, FX, liquidity and equities.",
      "published": "2026-06-29T10:05:45.709028Z"
    },
    {
      "id": "30e792a2341df914a70560d25e51a6ba",
      "title": "China's economy picks up in June on rebounding U.S. exports, analysts say",
      "summary": "China's economy is showing signs of picking up after a sluggish few months \u2014 thanks in part to a rebound in shipments to the U.S.",
      "link": "https://www.cnbc.com/2026/06/29/china-economy-june-trade-exports-manufacturing-tariffs-iran-war-consumption-ai-technology-.html",
      "source": "CNBC",
      "score": 12,
      "severity": "MEDIUM",
      "regime": "GEO-SHOCK",
      "tickers": [],
      "regions": [
        "CHINA"
      ],
      "assets": [],
      "market_impact": {
        "bullish": [
          "XAU",
          "WTI",
          "DXY",
          "DEFENSE"
        ],
        "bearish": [
          "SPY",
          "QQQ",
          "AIRLINES"
        ]
      },
      "why_it_matters": "Geopolitical escalation affecting commodities, shipping and cross-asset volatility.",
      "published": "2026-06-29T10:05:49.154587Z"
    },
    {
      "id": "7c133b16b49fd9cd91c524f4d2c37607",
      "title": "Europe\u2019s unlicensed crypto firms face \u2018wipeout\u2019 as MiCA deadline hits",
      "summary": "",
      "link": "https://www.coindesk.com/policy/2026/06/29/europe-s-unlicensed-crypto-firms-face-wipeout-as-final-regulatory-deadline-falls",
      "source": "CoinDesk",
      "score": 11,
      "severity": "MEDIUM",
      "regime": "CRYPTO",
      "tickers": [
        "EUR"
      ],
      "regions": [
        "EUROPE"
      ],
      "assets": [
        "FX"
      ],
      "market_impact": {
        "bullish": [
          "BTC",
          "ETH"
        ],
        "bearish": [
          "USD"
        ]
      },
      "why_it_matters": "Digital asset volatility and institutional crypto positioning changes.",
      "published": "2026-06-29T10:06:19.440262Z"
    },
    {
      "id": "d6944856caafa960a39d2da188c2c977",
      "title": "BTC price RSI prints key 2026 signal: Five things to know in Bitcoin this week",
      "summary": "<p style=\"float: right; margin: 0 0 10px 15px; width: 240px;\"><img alt=\"BTC price RSI prints key 2026 signal: Five things to know in Bitcoin this week\" class=\"type:primaryImage\" src=\"https://s3-images.ctmedia.io/media/article-covers/bitcoin-lazer-eyes-and-bull-run1.jpg\" /></p><p>Bitcoin prepped an \"interesting\" RSI divergence into the Q2 and June candle close as analysis compared $60,000 to the $30,000 mark in the 2022 bear market.</p>",
      "link": "https://cointelegraph.com/markets/btc-price-rsi-prints-key-2026-signal-five-things-to-know-in-bitcoin-this-week?utm_source=rss_feed&utm_medium=rss&utm_campaign=rss_partner_inbound",
      "source": "CoinTelegraph",
      "score": 7,
      "severity": "LOW",
      "regime": "CRYPTO",
      "tickers": [
        "BTC"
      ],
      "regions": [],
      "assets": [
        "CRYPTO"
      ],
      "market_impact": {
        "bullish": [
          "BTC",
          "ETH"
        ],
        "bearish": [
          "USD"
        ]
      },
      "why_it_matters": "Digital asset volatility and institutional crypto positioning changes.",
      "published": "2026-06-29T10:06:19.549507Z"
    }
  ],
  "alerts": [
    {
      "id": "102bee1ec6a6816b4af992be4b2eb2c8",
      "title": "Dip Buyers Lift US Stocks Despite Rise in Oil: Markets Wrap",
      "summary": "Bargain hunters are pushing stocks higher at the start of a week in which leaders of the biggest central banks and a busy data calendar will set the tone. Oil rose after a weekend of tensions in the Middle East.",
      "link": "https://www.bloomberg.com/news/articles/2026-06-28/us-futures-climb-on-reports-peace-talks-to-resume-markets-wrap",
      "source": "Bloomberg",
      "score": 30,
      "severity": "CRITICAL",
      "regime": "GEO-SHOCK",
      "tickers": [
        "WTI"
      ],
      "regions": [],
      "assets": [
        "AI",
        "COMMODITIES",
        "EQUITIES"
      ],
      "market_impact": {
        "bullish": [
          "XAU",
          "WTI",
          "DXY",
          "DEFENSE"
        ],
        "bearish": [
          "SPY",
          "QQQ",
          "AIRLINES"
        ]
      },
      "why_it_matters": "Geopolitical escalation affecting commodities, shipping and cross-asset volatility.",
      "published": "2026-06-29T10:05:45.708993Z"
    },
    {
      "id": "39b329c8183c0fe4d5ecc0764a4204d7",
      "title": "UK Bond Yields Higher Ahead of Burnham Speech",
      "summary": "",
      "link": "https://www.bloomberg.com/news/live-blog/2026-06-29/ftse-100-live-pound-glits-us-iran-talks-hormuz-oil-prices-gold-what-s-moving-uk-markets-right-now-markets-today",
      "source": "Bloomberg",
      "score": 15,
      "severity": "HIGH",
      "regime": "RATES",
      "tickers": [],
      "regions": [
        "UK"
      ],
      "assets": [],
      "market_impact": {
        "bullish": [
          "DXY",
          "JPY"
        ],
        "bearish": [
          "TLT",
          "SPY",
          "QQQ"
        ]
      },
      "why_it_matters": "Central-bank repricing affecting yields, FX, liquidity and equities.",
      "published": "2026-06-29T10:05:45.709028Z"
    },
    {
      "id": "30e792a2341df914a70560d25e51a6ba",
      "title": "China's economy picks up in June on rebounding U.S. exports, analysts say",
      "summary": "China's economy is showing signs of picking up after a sluggish few months \u2014 thanks in part to a rebound in shipments to the U.S.",
      "link": "https://www.cnbc.com/2026/06/29/china-economy-june-trade-exports-manufacturing-tariffs-iran-war-consumption-ai-technology-.html",
      "source": "CNBC",
      "score": 12,
      "severity": "MEDIUM",
      "regime": "GEO-SHOCK",
      "tickers": [],
      "regions": [
        "CHINA"
      ],
      "assets": [],
      "market_impact": {
        "bullish": [
          "XAU",
          "WTI",
          "DXY",
          "DEFENSE"
        ],
        "bearish": [
          "SPY",
          "QQQ",
          "AIRLINES"
        ]
      },
      "why_it_matters": "Geopolitical escalation affecting commodities, shipping and cross-asset volatility.",
      "published": "2026-06-29T10:05:49.154587Z"
    },
    {
      "id": "7c133b16b49fd9cd91c524f4d2c37607",
      "title": "Europe\u2019s unlicensed crypto firms face \u2018wipeout\u2019 as MiCA deadline hits",
      "summary": "",
      "link": "https://www.coindesk.com/policy/2026/06/29/europe-s-unlicensed-crypto-firms-face-wipeout-as-final-regulatory-deadline-falls",
      "source": "CoinDesk",
      "score": 11,
      "severity": "MEDIUM",
      "regime": "CRYPTO",
      "tickers": [
        "EUR"
      ],
      "regions": [
        "EUROPE"
      ],
      "assets": [
        "FX"
      ],
      "market_impact": {
        "bullish": [
          "BTC",
          "ETH"
        ],
        "bearish": [
          "USD"
        ]
      },
      "why_it_matters": "Digital asset volatility and institutional crypto positioning changes.",
      "published": "2026-06-29T10:06:19.440262Z"
    },
    {
      "id": "d6944856caafa960a39d2da188c2c977",
      "title": "BTC price RSI prints key 2026 signal: Five things to know in Bitcoin this week",
      "summary": "<p style=\"float: right; margin: 0 0 10px 15px; width: 240px;\"><img alt=\"BTC price RSI prints key 2026 signal: Five things to know in Bitcoin this week\" class=\"type:primaryImage\" src=\"https://s3-images.ctmedia.io/media/article-covers/bitcoin-lazer-eyes-and-bull-run1.jpg\" /></p><p>Bitcoin prepped an \"interesting\" RSI divergence into the Q2 and June candle close as analysis compared $60,000 to the $30,000 mark in the 2022 bear market.</p>",
      "link": "https://cointelegraph.com/markets/btc-price-rsi-prints-key-2026-signal-five-things-to-know-in-bitcoin-this-week?utm_source=rss_feed&utm_medium=rss&utm_campaign=rss_partner_inbound",
      "source": "CoinTelegraph",
      "score": 7,
      "severity": "LOW",
      "regime": "CRYPTO",
      "tickers": [
        "BTC"
      ],
      "regions": [],
      "assets": [
        "CRYPTO"
      ],
      "market_impact": {
        "bullish": [
          "BTC",
          "ETH"
        ],
        "bearish": [
          "USD"
        ]
      },
      "why_it_matters": "Digital asset volatility and institutional crypto positioning changes.",
      "published": "2026-06-29T10:06:19.549507Z"
    }
  ]
}