{
  "terminal": "Institutional Macro Terminal",
  "generated_at": "2026-05-27T20:41:20.258918Z",
  "market_regime": {
    "regime": "COMMODITIES",
    "dominant_driver": "COMMODITIES",
    "secondary_driver": "GENERAL",
    "signal_density": "LOW",
    "critical_alerts": 1,
    "high_alerts": 0,
    "last_updated": "2026-05-27T20:41:20.258932Z"
  },
  "top_signals": [
    {
      "id": "f0bf3bd05a3a1cf5a173651c7fbd7c44",
      "title": "Oil falls as Iranian state television reports details of peace proposal",
      "summary": "Broadcast said draft deal would restore Strait of Hormuz shipping within a month",
      "link": "https://www.ft.com/content/c79efc18-7c4f-4ff6-8f12-687892b5bd6f",
      "source": "Financial Times",
      "score": 39,
      "severity": "CRITICAL",
      "regime": "COMMODITIES",
      "tickers": [
        "WTI"
      ],
      "regions": [
        "MIDDLE_EAST"
      ],
      "assets": [
        "AI",
        "COMMODITIES",
        "SHIPPING"
      ],
      "market_impact": {
        "bullish": [
          "WTI",
          "XAU",
          "MINERS"
        ],
        "bearish": [
          "AIRLINES",
          "TRANSPORT"
        ]
      },
      "why_it_matters": "Commodity repricing impacting inflation expectations and industrial supply chains.",
      "published": "2026-05-27T20:40:29.299678Z"
    },
    {
      "id": "2aa0f277d8722101428e84aa092e2d3d",
      "title": "A bipartisan bridge to the future: Why the Senate must finish the job on digital Assets",
      "summary": "",
      "link": "https://www.coindesk.com/opinion/2026/05/27/a-bipartisan-bridge-to-the-future-why-the-senate-must-finish-the-job-on-digital-assets",
      "source": "CoinDesk",
      "score": 6,
      "severity": "LOW",
      "regime": "GENERAL",
      "tickers": [],
      "regions": [],
      "assets": [],
      "market_impact": {},
      "why_it_matters": "Macro-sensitive market development.",
      "published": "2026-05-27T20:41:16.438187Z"
    },
    {
      "id": "59107d52dd6360d4a9fb8363584829ab",
      "title": "Reflecting on Sherwin-Williams Protective & Marine's History with the Department of Defense",
      "summary": "Sherwin-Williams Protective & Marine partners with the U.S. Department of Defense (DoD) by supplying high-performance, MIL-Spec-approved coatings for a variety of platforms such as aircraft carriers, submarines, armored vehicles and aircraft.",
      "link": "https://www.marinelink.com/news/reflecting-sherwinwilliams-protective-539656",
      "source": "MarineLink",
      "score": 5,
      "severity": "LOW",
      "regime": "AI",
      "tickers": [],
      "regions": [],
      "assets": [
        "AI"
      ],
      "market_impact": {
        "bullish": [
          "NVDA",
          "SEMIS",
          "QQQ"
        ],
        "bearish": []
      },
      "why_it_matters": "AI and semiconductor developments impacting technology leadership and capex cycles.",
      "published": "2026-05-27T20:41:15.016891Z"
    },
    {
      "id": "eefa6da4c259ad366a1cfc81c88315d9",
      "title": "Windows 11 KB5089573 update released with performance improvements",
      "summary": "Microsoft has released the KB5089573 preview cumulative update for Windows 11 versions 25H2 and 24H2, which comes with 30 changes, including performance and reliability improvements. [...]",
      "link": "https://www.bleepingcomputer.com/news/microsoft/windows-11-kb5089573-update-released-with-performance-improvements/",
      "source": "BleepingComputer",
      "score": 1,
      "severity": "LOW",
      "regime": "GENERAL",
      "tickers": [],
      "regions": [],
      "assets": [],
      "market_impact": {},
      "why_it_matters": "Macro-sensitive market development.",
      "published": "2026-05-27T20:41:16.826931Z"
    }
  ],
  "alerts": [
    {
      "id": "f0bf3bd05a3a1cf5a173651c7fbd7c44",
      "title": "Oil falls as Iranian state television reports details of peace proposal",
      "summary": "Broadcast said draft deal would restore Strait of Hormuz shipping within a month",
      "link": "https://www.ft.com/content/c79efc18-7c4f-4ff6-8f12-687892b5bd6f",
      "source": "Financial Times",
      "score": 39,
      "severity": "CRITICAL",
      "regime": "COMMODITIES",
      "tickers": [
        "WTI"
      ],
      "regions": [
        "MIDDLE_EAST"
      ],
      "assets": [
        "AI",
        "COMMODITIES",
        "SHIPPING"
      ],
      "market_impact": {
        "bullish": [
          "WTI",
          "XAU",
          "MINERS"
        ],
        "bearish": [
          "AIRLINES",
          "TRANSPORT"
        ]
      },
      "why_it_matters": "Commodity repricing impacting inflation expectations and industrial supply chains.",
      "published": "2026-05-27T20:40:29.299678Z"
    },
    {
      "id": "2aa0f277d8722101428e84aa092e2d3d",
      "title": "A bipartisan bridge to the future: Why the Senate must finish the job on digital Assets",
      "summary": "",
      "link": "https://www.coindesk.com/opinion/2026/05/27/a-bipartisan-bridge-to-the-future-why-the-senate-must-finish-the-job-on-digital-assets",
      "source": "CoinDesk",
      "score": 6,
      "severity": "LOW",
      "regime": "GENERAL",
      "tickers": [],
      "regions": [],
      "assets": [],
      "market_impact": {},
      "why_it_matters": "Macro-sensitive market development.",
      "published": "2026-05-27T20:41:16.438187Z"
    },
    {
      "id": "59107d52dd6360d4a9fb8363584829ab",
      "title": "Reflecting on Sherwin-Williams Protective & Marine's History with the Department of Defense",
      "summary": "Sherwin-Williams Protective & Marine partners with the U.S. Department of Defense (DoD) by supplying high-performance, MIL-Spec-approved coatings for a variety of platforms such as aircraft carriers, submarines, armored vehicles and aircraft.",
      "link": "https://www.marinelink.com/news/reflecting-sherwinwilliams-protective-539656",
      "source": "MarineLink",
      "score": 5,
      "severity": "LOW",
      "regime": "AI",
      "tickers": [],
      "regions": [],
      "assets": [
        "AI"
      ],
      "market_impact": {
        "bullish": [
          "NVDA",
          "SEMIS",
          "QQQ"
        ],
        "bearish": []
      },
      "why_it_matters": "AI and semiconductor developments impacting technology leadership and capex cycles.",
      "published": "2026-05-27T20:41:15.016891Z"
    },
    {
      "id": "eefa6da4c259ad366a1cfc81c88315d9",
      "title": "Windows 11 KB5089573 update released with performance improvements",
      "summary": "Microsoft has released the KB5089573 preview cumulative update for Windows 11 versions 25H2 and 24H2, which comes with 30 changes, including performance and reliability improvements. [...]",
      "link": "https://www.bleepingcomputer.com/news/microsoft/windows-11-kb5089573-update-released-with-performance-improvements/",
      "source": "BleepingComputer",
      "score": 1,
      "severity": "LOW",
      "regime": "GENERAL",
      "tickers": [],
      "regions": [],
      "assets": [],
      "market_impact": {},
      "why_it_matters": "Macro-sensitive market development.",
      "published": "2026-05-27T20:41:16.826931Z"
    }
  ]
}