{
  "terminal": "Institutional Macro Terminal",
  "generated_at": "2026-05-27T08:31:11.279473Z",
  "market_regime": {
    "regime": "COMMODITIES",
    "dominant_driver": "COMMODITIES",
    "secondary_driver": "GENERAL",
    "signal_density": "LOW",
    "critical_alerts": 0,
    "high_alerts": 1,
    "last_updated": "2026-05-27T08:31:11.279488Z"
  },
  "top_signals": [
    {
      "id": "118f725243612a73f58e41a6cbcdfda1",
      "title": "Goldman Strategists Lift S&amp;P 500 Target to 8,000 on AI, Earnings",
      "summary": "Strategists at Goldman Sachs Group Inc. joined peers at Morgan Stanley and Deutsche Bank AG in seeing a 17% return for the S&amp;P 500 Index this year.",
      "link": "https://www.bloomberg.com/news/articles/2026-05-27/goldman-strategists-lift-s-p-500-target-to-8-000-on-ai-earnings",
      "source": "Bloomberg",
      "score": 19,
      "severity": "HIGH",
      "regime": "COMMODITIES",
      "tickers": [
        "XAU"
      ],
      "regions": [],
      "assets": [
        "AI",
        "COMMODITIES"
      ],
      "market_impact": {
        "bullish": [
          "WTI",
          "XAU",
          "MINERS"
        ],
        "bearish": [
          "AIRLINES",
          "TRANSPORT"
        ]
      },
      "why_it_matters": "Commodity repricing impacting inflation expectations and industrial supply chains.",
      "published": "2026-05-27T08:30:37.474499Z"
    },
    {
      "id": "47778b6b47204b5e1f76a87e88532781",
      "title": "Dulux owner AkzoNobel rejects \u20ac13bn attempt to gatecrash merger",
      "summary": "Shares jump as Nippon Paint and Sherwin-Williams attempt to muscle in on deal between Dutch group and Axalta",
      "link": "https://www.ft.com/content/2b229ee4-fc74-4fc3-96b5-96cbe9ef88d2",
      "source": "Financial Times",
      "score": 12,
      "severity": "MEDIUM",
      "regime": "AI",
      "tickers": [],
      "regions": [],
      "assets": [
        "AI"
      ],
      "market_impact": {
        "bullish": [
          "NVDA",
          "SEMIS",
          "QQQ"
        ],
        "bearish": []
      },
      "why_it_matters": "AI and semiconductor developments impacting technology leadership and capex cycles.",
      "published": "2026-05-27T08:30:39.658722Z"
    },
    {
      "id": "646e542fef15ef84581d6006c2b65648",
      "title": "Australia starts \u2018high-risk\u2019 life extension of its submarine fleet",
      "summary": "The Australian National Audit Office (ANAO) has issued a damning verdict on Department of Defence planning for the life-extension program.",
      "link": "https://www.defensenews.com/global/asia-pacific/2026/05/26/australia-starts-high-risk-life-extension-of-its-submarine-fleet/",
      "source": "Defense News",
      "score": 6,
      "severity": "LOW",
      "regime": "GENERAL",
      "tickers": [],
      "regions": [],
      "assets": [],
      "market_impact": {},
      "why_it_matters": "Macro-sensitive market development.",
      "published": "2026-05-27T08:31:06.951749Z"
    }
  ],
  "alerts": [
    {
      "id": "118f725243612a73f58e41a6cbcdfda1",
      "title": "Goldman Strategists Lift S&amp;P 500 Target to 8,000 on AI, Earnings",
      "summary": "Strategists at Goldman Sachs Group Inc. joined peers at Morgan Stanley and Deutsche Bank AG in seeing a 17% return for the S&amp;P 500 Index this year.",
      "link": "https://www.bloomberg.com/news/articles/2026-05-27/goldman-strategists-lift-s-p-500-target-to-8-000-on-ai-earnings",
      "source": "Bloomberg",
      "score": 19,
      "severity": "HIGH",
      "regime": "COMMODITIES",
      "tickers": [
        "XAU"
      ],
      "regions": [],
      "assets": [
        "AI",
        "COMMODITIES"
      ],
      "market_impact": {
        "bullish": [
          "WTI",
          "XAU",
          "MINERS"
        ],
        "bearish": [
          "AIRLINES",
          "TRANSPORT"
        ]
      },
      "why_it_matters": "Commodity repricing impacting inflation expectations and industrial supply chains.",
      "published": "2026-05-27T08:30:37.474499Z"
    },
    {
      "id": "47778b6b47204b5e1f76a87e88532781",
      "title": "Dulux owner AkzoNobel rejects \u20ac13bn attempt to gatecrash merger",
      "summary": "Shares jump as Nippon Paint and Sherwin-Williams attempt to muscle in on deal between Dutch group and Axalta",
      "link": "https://www.ft.com/content/2b229ee4-fc74-4fc3-96b5-96cbe9ef88d2",
      "source": "Financial Times",
      "score": 12,
      "severity": "MEDIUM",
      "regime": "AI",
      "tickers": [],
      "regions": [],
      "assets": [
        "AI"
      ],
      "market_impact": {
        "bullish": [
          "NVDA",
          "SEMIS",
          "QQQ"
        ],
        "bearish": []
      },
      "why_it_matters": "AI and semiconductor developments impacting technology leadership and capex cycles.",
      "published": "2026-05-27T08:30:39.658722Z"
    },
    {
      "id": "646e542fef15ef84581d6006c2b65648",
      "title": "Australia starts \u2018high-risk\u2019 life extension of its submarine fleet",
      "summary": "The Australian National Audit Office (ANAO) has issued a damning verdict on Department of Defence planning for the life-extension program.",
      "link": "https://www.defensenews.com/global/asia-pacific/2026/05/26/australia-starts-high-risk-life-extension-of-its-submarine-fleet/",
      "source": "Defense News",
      "score": 6,
      "severity": "LOW",
      "regime": "GENERAL",
      "tickers": [],
      "regions": [],
      "assets": [],
      "market_impact": {},
      "why_it_matters": "Macro-sensitive market development.",
      "published": "2026-05-27T08:31:06.951749Z"
    }
  ]
}