{
  "terminal": "Institutional Macro Terminal",
  "generated_at": "2026-07-09T01:56:36.496273Z",
  "market_regime": {
    "regime": "GEO-SHOCK",
    "dominant_driver": "GEO-SHOCK",
    "secondary_driver": "GENERAL",
    "signal_density": "LOW",
    "critical_alerts": 0,
    "high_alerts": 0,
    "last_updated": "2026-07-09T01:56:36.496285Z"
  },
  "top_signals": [
    {
      "id": "b5de06792197d8c18764b2c9c5cdf0ea",
      "title": "Fake Paysafe, Skrill SDKs on NPM and PyPi steal credentials",
      "summary": "Malicious packages on the Node Package Manager (npm) and the Python Package Index (PyPI) delivered stealer malware to developers and users of Paysafe, Skrill, and Neteller payment applications. [...]",
      "link": "https://www.bleepingcomputer.com/news/security/fake-paysafe-skrill-sdks-on-npm-and-pypi-steal-credentials/",
      "source": "BleepingComputer",
      "score": 11,
      "severity": "MEDIUM",
      "regime": "GEO-SHOCK",
      "tickers": [],
      "regions": [],
      "assets": [],
      "market_impact": {
        "bullish": [
          "XAU",
          "WTI",
          "DXY",
          "DEFENSE"
        ],
        "bearish": [
          "SPY",
          "QQQ",
          "AIRLINES"
        ]
      },
      "why_it_matters": "Geopolitical escalation affecting commodities, shipping and cross-asset volatility.",
      "published": "2026-07-09T01:56:32.647197Z"
    },
    {
      "id": "03dddbe624f073a2a894e51969d7e717",
      "title": "Shoppers splurge on specs in Japan as deflation-era mindset fades away",
      "summary": "As inflation reshapes behavior, Japanese eyeglass company Jins is working to prove higher prices are justified by delivering better materials, sharper designs and improved quality.",
      "link": "https://www.japantimes.co.jp/business/2026/07/09/economy/jins-glasses-shopping/",
      "source": "Japan Times",
      "score": 8,
      "severity": "MEDIUM",
      "regime": "INFLATION",
      "tickers": [],
      "regions": [
        "JAPAN"
      ],
      "assets": [],
      "market_impact": {
        "bullish": [
          "XAU",
          "WTI",
          "COMMODITIES"
        ],
        "bearish": [
          "BONDS",
          "GROWTH"
        ]
      },
      "why_it_matters": "Inflation expectations impacting rate path, bonds and global risk assets.",
      "published": "2026-07-09T01:56:20.417582Z"
    },
    {
      "id": "156cc6cd4bb1d6bee45379cac0300321",
      "title": "Speech by Commissioner V\u00e1rhelyi at the Conference on Animal Health Law",
      "summary": "European Commission Speech Brussels, 08 Jul 2026 Good morning, ladies and gentlemen,\nWelcome to this conference on the Animal Health Law.\nIt is a pleasure to welcome such a broad range of partners today - from...",
      "link": "https://ec.europa.eu/commission/presscorner/detail/en/speech_26_1559",
      "source": "European Commission",
      "score": 1,
      "severity": "LOW",
      "regime": "GENERAL",
      "tickers": [
        "EUR"
      ],
      "regions": [
        "EUROPE"
      ],
      "assets": [
        "FX"
      ],
      "market_impact": {},
      "why_it_matters": "Macro-sensitive market development.",
      "published": "2026-07-09T01:56:16.682207Z"
    }
  ],
  "alerts": [
    {
      "id": "b5de06792197d8c18764b2c9c5cdf0ea",
      "title": "Fake Paysafe, Skrill SDKs on NPM and PyPi steal credentials",
      "summary": "Malicious packages on the Node Package Manager (npm) and the Python Package Index (PyPI) delivered stealer malware to developers and users of Paysafe, Skrill, and Neteller payment applications. [...]",
      "link": "https://www.bleepingcomputer.com/news/security/fake-paysafe-skrill-sdks-on-npm-and-pypi-steal-credentials/",
      "source": "BleepingComputer",
      "score": 11,
      "severity": "MEDIUM",
      "regime": "GEO-SHOCK",
      "tickers": [],
      "regions": [],
      "assets": [],
      "market_impact": {
        "bullish": [
          "XAU",
          "WTI",
          "DXY",
          "DEFENSE"
        ],
        "bearish": [
          "SPY",
          "QQQ",
          "AIRLINES"
        ]
      },
      "why_it_matters": "Geopolitical escalation affecting commodities, shipping and cross-asset volatility.",
      "published": "2026-07-09T01:56:32.647197Z"
    },
    {
      "id": "03dddbe624f073a2a894e51969d7e717",
      "title": "Shoppers splurge on specs in Japan as deflation-era mindset fades away",
      "summary": "As inflation reshapes behavior, Japanese eyeglass company Jins is working to prove higher prices are justified by delivering better materials, sharper designs and improved quality.",
      "link": "https://www.japantimes.co.jp/business/2026/07/09/economy/jins-glasses-shopping/",
      "source": "Japan Times",
      "score": 8,
      "severity": "MEDIUM",
      "regime": "INFLATION",
      "tickers": [],
      "regions": [
        "JAPAN"
      ],
      "assets": [],
      "market_impact": {
        "bullish": [
          "XAU",
          "WTI",
          "COMMODITIES"
        ],
        "bearish": [
          "BONDS",
          "GROWTH"
        ]
      },
      "why_it_matters": "Inflation expectations impacting rate path, bonds and global risk assets.",
      "published": "2026-07-09T01:56:20.417582Z"
    },
    {
      "id": "156cc6cd4bb1d6bee45379cac0300321",
      "title": "Speech by Commissioner V\u00e1rhelyi at the Conference on Animal Health Law",
      "summary": "European Commission Speech Brussels, 08 Jul 2026 Good morning, ladies and gentlemen,\nWelcome to this conference on the Animal Health Law.\nIt is a pleasure to welcome such a broad range of partners today - from...",
      "link": "https://ec.europa.eu/commission/presscorner/detail/en/speech_26_1559",
      "source": "European Commission",
      "score": 1,
      "severity": "LOW",
      "regime": "GENERAL",
      "tickers": [
        "EUR"
      ],
      "regions": [
        "EUROPE"
      ],
      "assets": [
        "FX"
      ],
      "market_impact": {},
      "why_it_matters": "Macro-sensitive market development.",
      "published": "2026-07-09T01:56:16.682207Z"
    }
  ]
}