{
  "terminal": "Institutional Macro Terminal",
  "generated_at": "2026-07-03T12:16:43.123599Z",
  "market_regime": {
    "regime": "COMMODITIES",
    "dominant_driver": "COMMODITIES",
    "secondary_driver": "GENERAL",
    "signal_density": "LOW",
    "critical_alerts": 0,
    "high_alerts": 1,
    "last_updated": "2026-07-03T12:16:43.123611Z"
  },
  "top_signals": [
    {
      "id": "6b2e7335769ca3b747a6cb8729240f34",
      "title": "Russia Hikes June Subsidies to Refiners as Fuel Shortages Bite",
      "summary": "Russia\u2019s subsidy payouts to oil refiners that supply domestic markets jumped more than six-fold in June from a year earlier, as Moscow sought to avoid shortages by keeping more fuel at home.",
      "link": "https://www.bloomberg.com/news/articles/2026-07-03/russia-hikes-june-subsidies-to-refiners-as-fuel-shortages-bite",
      "source": "Bloomberg",
      "score": 24,
      "severity": "HIGH",
      "regime": "COMMODITIES",
      "tickers": [
        "WTI"
      ],
      "regions": [
        "RUSSIA"
      ],
      "assets": [
        "COMMODITIES"
      ],
      "market_impact": {
        "bullish": [
          "WTI",
          "XAU",
          "MINERS"
        ],
        "bearish": [
          "AIRLINES",
          "TRANSPORT"
        ]
      },
      "why_it_matters": "Commodity repricing impacting inflation expectations and industrial supply chains.",
      "published": "2026-07-03T12:16:00.573996Z"
    },
    {
      "id": "0f060f29857abdc0bd29109084f36b15",
      "title": "Pubs to Get Short-Term World Cup Boost",
      "summary": "UK pubs will be allowed to stay open for Monday\u2019s early morning match, but the overall benefit of the World Cup will likely be short-lived. Bloomberg's Sam Unsed discusses on \"The Opening Trade.\" (Source: Bloomberg)",
      "link": "https://www.bloomberg.com/news/videos/2026-07-03/pubs-to-get-short-term-world-cup-boost-video",
      "source": "Bloomberg",
      "score": 9,
      "severity": "MEDIUM",
      "regime": "GENERAL",
      "tickers": [],
      "regions": [
        "UK"
      ],
      "assets": [],
      "market_impact": {},
      "why_it_matters": "Macro-sensitive market development.",
      "published": "2026-07-03T12:16:00.573908Z"
    },
    {
      "id": "c82f639770c0e8e87c43ec4a2e53fb89",
      "title": "StanChart joins ESMA's first MiCA register update since deadline",
      "summary": "<p style=\"float: right; margin: 0 0 10px 15px; width: 240px;\"><img alt=\"StanChart joins ESMA's first MiCA register update since deadline\" class=\"type:primaryImage\" src=\"https://s3-images.ctmedia.io/media/article-covers/hi-protecting-your-crypto-investment3333.jpg\" /></p><p>ESMA publishes its first post-deadline MiCA register update, adding 37 crypto-asset service providers, including Standard Chartered and FalconX.</p>",
      "link": "https://cointelegraph.com/news/esma-mica-register-new-casps-stanchart-update?utm_source=rss_feed&utm_medium=rss&utm_campaign=rss_partner_inbound",
      "source": "CoinTelegraph",
      "score": 6,
      "severity": "LOW",
      "regime": "CRYPTO",
      "tickers": [],
      "regions": [],
      "assets": [],
      "market_impact": {
        "bullish": [
          "BTC",
          "ETH"
        ],
        "bearish": [
          "USD"
        ]
      },
      "why_it_matters": "Digital asset volatility and institutional crypto positioning changes.",
      "published": "2026-07-03T12:16:39.224288Z"
    },
    {
      "id": "38db2649602b6d030eef4283023723b3",
      "title": "The Wall Street Journal & Breaking News, Business, Financial and Economic News, World News and Video - WSJ",
      "summary": "<a href=\"https://news.google.com/rss/articles/CBMiN0FVX3lxTE90Y3MxWTNmYjZIUEhwbU13WHFsQ1ZqamxiaFowSEdKeDR4LUF6QzV0UmZzX0Vjd0E?oc=5\" target=\"_blank\">The Wall Street Journal & Breaking News, Business, Financial and Economic News, World News and Video</a>&nbsp;&nbsp;<font color=\"#6f6f6f\">WSJ</font>",
      "link": "https://news.google.com/rss/articles/CBMiN0FVX3lxTE90Y3MxWTNmYjZIUEhwbU13WHFsQ1ZqamxiaFowSEdKeDR4LUF6QzV0UmZzX0Vjd0E?oc=5",
      "source": "Google Macro",
      "score": 1,
      "severity": "LOW",
      "regime": "GENERAL",
      "tickers": [],
      "regions": [],
      "assets": [],
      "market_impact": {},
      "why_it_matters": "Macro-sensitive market development.",
      "published": "2026-07-03T12:16:42.544408Z"
    }
  ],
  "alerts": [
    {
      "id": "6b2e7335769ca3b747a6cb8729240f34",
      "title": "Russia Hikes June Subsidies to Refiners as Fuel Shortages Bite",
      "summary": "Russia\u2019s subsidy payouts to oil refiners that supply domestic markets jumped more than six-fold in June from a year earlier, as Moscow sought to avoid shortages by keeping more fuel at home.",
      "link": "https://www.bloomberg.com/news/articles/2026-07-03/russia-hikes-june-subsidies-to-refiners-as-fuel-shortages-bite",
      "source": "Bloomberg",
      "score": 24,
      "severity": "HIGH",
      "regime": "COMMODITIES",
      "tickers": [
        "WTI"
      ],
      "regions": [
        "RUSSIA"
      ],
      "assets": [
        "COMMODITIES"
      ],
      "market_impact": {
        "bullish": [
          "WTI",
          "XAU",
          "MINERS"
        ],
        "bearish": [
          "AIRLINES",
          "TRANSPORT"
        ]
      },
      "why_it_matters": "Commodity repricing impacting inflation expectations and industrial supply chains.",
      "published": "2026-07-03T12:16:00.573996Z"
    },
    {
      "id": "0f060f29857abdc0bd29109084f36b15",
      "title": "Pubs to Get Short-Term World Cup Boost",
      "summary": "UK pubs will be allowed to stay open for Monday\u2019s early morning match, but the overall benefit of the World Cup will likely be short-lived. Bloomberg's Sam Unsed discusses on \"The Opening Trade.\" (Source: Bloomberg)",
      "link": "https://www.bloomberg.com/news/videos/2026-07-03/pubs-to-get-short-term-world-cup-boost-video",
      "source": "Bloomberg",
      "score": 9,
      "severity": "MEDIUM",
      "regime": "GENERAL",
      "tickers": [],
      "regions": [
        "UK"
      ],
      "assets": [],
      "market_impact": {},
      "why_it_matters": "Macro-sensitive market development.",
      "published": "2026-07-03T12:16:00.573908Z"
    },
    {
      "id": "c82f639770c0e8e87c43ec4a2e53fb89",
      "title": "StanChart joins ESMA's first MiCA register update since deadline",
      "summary": "<p style=\"float: right; margin: 0 0 10px 15px; width: 240px;\"><img alt=\"StanChart joins ESMA's first MiCA register update since deadline\" class=\"type:primaryImage\" src=\"https://s3-images.ctmedia.io/media/article-covers/hi-protecting-your-crypto-investment3333.jpg\" /></p><p>ESMA publishes its first post-deadline MiCA register update, adding 37 crypto-asset service providers, including Standard Chartered and FalconX.</p>",
      "link": "https://cointelegraph.com/news/esma-mica-register-new-casps-stanchart-update?utm_source=rss_feed&utm_medium=rss&utm_campaign=rss_partner_inbound",
      "source": "CoinTelegraph",
      "score": 6,
      "severity": "LOW",
      "regime": "CRYPTO",
      "tickers": [],
      "regions": [],
      "assets": [],
      "market_impact": {
        "bullish": [
          "BTC",
          "ETH"
        ],
        "bearish": [
          "USD"
        ]
      },
      "why_it_matters": "Digital asset volatility and institutional crypto positioning changes.",
      "published": "2026-07-03T12:16:39.224288Z"
    },
    {
      "id": "38db2649602b6d030eef4283023723b3",
      "title": "The Wall Street Journal & Breaking News, Business, Financial and Economic News, World News and Video - WSJ",
      "summary": "<a href=\"https://news.google.com/rss/articles/CBMiN0FVX3lxTE90Y3MxWTNmYjZIUEhwbU13WHFsQ1ZqamxiaFowSEdKeDR4LUF6QzV0UmZzX0Vjd0E?oc=5\" target=\"_blank\">The Wall Street Journal & Breaking News, Business, Financial and Economic News, World News and Video</a>&nbsp;&nbsp;<font color=\"#6f6f6f\">WSJ</font>",
      "link": "https://news.google.com/rss/articles/CBMiN0FVX3lxTE90Y3MxWTNmYjZIUEhwbU13WHFsQ1ZqamxiaFowSEdKeDR4LUF6QzV0UmZzX0Vjd0E?oc=5",
      "source": "Google Macro",
      "score": 1,
      "severity": "LOW",
      "regime": "GENERAL",
      "tickers": [],
      "regions": [],
      "assets": [],
      "market_impact": {},
      "why_it_matters": "Macro-sensitive market development.",
      "published": "2026-07-03T12:16:42.544408Z"
    }
  ]
}